openipdm/.DS_Store
openipdm/__init__.py
openipdm/data/Pretrained_SSMKR.mat
openipdm/data/service_life.mat
openipdm/ssm_kr.py
openipdm-0.0.1.dist-info/LICENSE
openipdm-0.0.1.dist-info/METADATA
openipdm-0.0.1.dist-info/WHEEL
openipdm-0.0.1.dist-info/RECORD
