Metadata-Version: 2.1
Name: openipdm
Version: 0.0.1
Summary: openipdm framework
License: MIT
Author: Zachary Hamida
Author-email: zac.hamida@gmail.com
Requires-Python: >=3.6,<4.0
Classifier: License :: OSI Approved :: MIT License
Classifier: Programming Language :: Python :: 3
Classifier: Programming Language :: Python :: 3.6
Classifier: Programming Language :: Python :: 3.7
Classifier: Programming Language :: Python :: 3.8
Classifier: Programming Language :: Python :: 3.9
Classifier: Programming Language :: Python :: 3.10
Classifier: Programming Language :: Python :: 3.11
Requires-Dist: altair (>=4.2.2,<5.0.0)
Requires-Dist: numpy (>=1.24.3,<2.0.0)
Requires-Dist: pandas (>=2.0.1,<3.0.0)
Requires-Dist: scipy (>=1.10.1,<2.0.0)
